SCAutolib/__init__.py
SCAutolib/cli_commands.py
SCAutolib/controller.py
SCAutolib/enums.py
SCAutolib/exceptions.py
SCAutolib/isDistro.py
SCAutolib/utils.py
SCAutolib/models/CA.py
SCAutolib/models/__init__.py
SCAutolib/models/authselect.py
SCAutolib/models/card.py
SCAutolib/models/file.py
SCAutolib/models/gui.py
SCAutolib/models/log.py
SCAutolib/models/user.py
SCAutolib/templates/ca.cnf
SCAutolib/templates/gnome_disable_welcome
SCAutolib/templates/softhsm2.conf
SCAutolib/templates/sssd.conf-10
SCAutolib/templates/sssd.conf-8or9
SCAutolib/templates/user.cnf
SCAutolib/templates/virt_cacard.service
SCAutolib/templates/virtcacard.cil
scautolib-3.4.2.dist-info/licenses/LICENSE
scautolib-3.4.2.dist-info/METADATA
scautolib-3.4.2.dist-info/WHEEL
scautolib-3.4.2.dist-info/entry_points.txt
scautolib-3.4.2.dist-info/top_level.txt
scautolib-3.4.2.dist-info/RECORD
