Metadata-Version: 2.4
Name: SCAutolib
Version: 3.4.2
Summary: Python library for automation tests of smart cards using virtualization.
Home-page: https://github.com/redhat-qe-security/SCAutolib
Author: Pavel Yadlouski
Author-email: pyadlous@redhat.com
Classifier: Programming Language :: Python :: 3
Classifier: Environment :: Console
Classifier: Framework :: Pytest
Classifier: Framework :: tox
Classifier: Intended Audience :: Developers
Classifier: Operating System :: Unix
Classifier: Topic :: Software Development :: Testing
Classifier: Topic :: Software Development :: Testing :: Acceptance
Requires-Python: >=3
License-File: LICENSE
Requires-Dist: click>=8
Requires-Dist: coloredlogs>=15
Requires-Dist: paramiko>=2.10
Requires-Dist: fabric>=2.7
Requires-Dist: invoke>=1.7
Requires-Dist: pytest>=7
Requires-Dist: schema>=0.7
Requires-Dist: python_freeipa>=1.0
Requires-Dist: pexpect>=4
Requires-Dist: distro>=1.5.0
Provides-Extra: graphical
Requires-Dist: opencv-python; extra == "graphical"
Requires-Dist: pandas; extra == "graphical"
Requires-Dist: numpy; extra == "graphical"
Requires-Dist: pytesseract; extra == "graphical"
Requires-Dist: keyboard; extra == "graphical"
Dynamic: author
Dynamic: author-email
Dynamic: classifier
Dynamic: description
Dynamic: description-content-type
Dynamic: home-page
Dynamic: license-file
Dynamic: provides-extra
Dynamic: requires-dist
Dynamic: requires-python
Dynamic: summary
